geodpy/__init__.py
geodpy/body.py
geodpy/geodesics.py
geodpy/to_lambda.py
geodpy/coordinates/__init__.py
geodpy/coordinates/cartesian.py
geodpy/coordinates/coordinates.py
geodpy/coordinates/lemaitre.py
geodpy/coordinates/oblong_ellipsoid.py
geodpy/coordinates/spherical.py
geodpy/plotters/__init__.py
geodpy/plotters/body_plotter.py
geodpy/plotters/plotters2D/__init__.py
geodpy/plotters/plotters2D/body_plotter_2D.py
geodpy/plotters/plotters2D/cartesian_plot_2D.py
geodpy/plotters/plotters2D/polar_plot.py
geodpy/plotters/plotters3D/__init__.py
geodpy/plotters/plotters3D/body_plotter_3D.py
geodpy/plotters/plotters3D/cartesian_plot_3D.py
geodpy/utilities/__init__.py
geodpy/utilities/base_run.py
geodpy/validationTests/__init__.py
geodpy/validationTests/schwarzschild.py
geodpy-1.0.3.dist-info/LICENSE
geodpy-1.0.3.dist-info/METADATA
geodpy-1.0.3.dist-info/WHEEL
geodpy-1.0.3.dist-info/top_level.txt
geodpy-1.0.3.dist-info/RECORD
