Metadata-Version: 2.1
Name: geodpy
Version: 1.0.3
Summary: Computes space-time geodesics given an arbitrary metric and initial conditions.
Author-email: Benjamin Gauthier <benjamin.gauthier@hotmail.ca>
License: MIT License
Project-URL: Homepage, https://github.com/Sneaker679/geodpy/tree/main
Keywords: general relativity,geodesics,geodesic,gr,astrophysics,astronomy,physics,riemann,riemann geometry,geometry,metric,space-time,spacetime
Classifier: License :: OSI Approved :: MIT License
Classifier: Programming Language :: Python
Classifier: Programming Language :: Python :: 3.12
Classifier: Programming Language :: Python :: 3
Classifier: Development Status :: 5 - Production/Stable
Classifier: Environment :: Console
Classifier: Intended Audience :: Science/Research
Classifier: Operating System :: POSIX :: Linux
Classifier: Topic :: Scientific/Engineering :: Mathematics
Classifier: Topic :: Scientific/Engineering :: Physics
Classifier: Topic :: Scientific/Engineering :: Astronomy
Requires-Python: >=3.12
License-File: LICENSE
Requires-Dist: numpy>=2.0.1
Requires-Dist: scipy>=1.14.0
Requires-Dist: sympy>=1.13.1
Requires-Dist: matplotlib>=3.9.1.post1
